SprinklrClient/SprinklrClient.py
SprinklrClient/__init__.py
SprinklrClient-0.21.5.17.5.dist-info/LICENSE
SprinklrClient-0.21.5.17.5.dist-info/METADATA
SprinklrClient-0.21.5.17.5.dist-info/WHEEL
SprinklrClient-0.21.5.17.5.dist-info/top_level.txt
SprinklrClient-0.21.5.17.5.dist-info/RECORD
