Metadata-Version: 2.1
Name: SprinklrClient
Version: 0.21.5.17.5
Summary: A Python client for using the Sprinklr API
Home-page: https://github.com/DzRepo/SprinklrClient
Author: Steven Dzilvelis
Author-email: steven_dzilvelis@hotmail.com
License: GNU
Project-URL: Bug Tracker, https://github.com/dzrepo/sprinklrclient/issues
Platform: UNKNOWN
Classifier: Programming Language :: Python :: 3
Classifier: License :: OSI Approved :: MIT License
Classifier: Operating System :: OS Independent
Requires-Python: >=3
Requires-Dist: requests
